{"stats":{"minecraft:dropped":{"minecraft:cobblestone":1},"minecraft:crafted":{"minecraft:crafting_table":1,"minecraft:spruce_planks":20,"minecraft:stick":12,"minecraft:wooden_pickaxe":1,"minecraft:stone_pickaxe":3,"minecraft:wooden_axe":1,"minecraft:torch":16},"minecraft:picked_up":{"minecraft:stick":2,"minecraft:crafting_table":2,"minecraft:torch":4,"minecraft:cooked_rabbit":1,"minecraft:spruce_sapling":5,"minecraft:spruce_log":88,"minecraft:raw_copper":9,"minecraft:rotten_flesh":2,"minecraft:coal":24,"minecraft:cobblestone":427},"minecraft:broken":{"minecraft:stone_pickaxe":3,"minecraft:wooden_axe":1,"minecraft:wooden_pickaxe":1},"minecraft:custom":{"minecraft:time_since_rest":16010,"minecraft:sprint_one_cm":16664,"minecraft:damage_taken":330,"minecraft:walk_one_cm":53549,"minecraft:mob_kills":1,"minecraft:drop":1,"minecraft:damage_dealt":184,"minecraft:interact_with_crafting_table":6,"minecraft:fly_one_cm":10924,"minecraft:crouch_one_cm":174,"minecraft:play_time":36567,"minecraft:deaths":2,"minecraft:sneak_time":250,"minecraft:walk_under_water_one_cm":500,"minecraft:jump":255,"minecraft:leave_game":2,"minecraft:walk_on_water_one_cm":1237,"minecraft:time_since_death":15963,"minecraft:total_world_time":36567,"minecraft:fall_one_cm":3877},"minecraft:used":{"minecraft:wooden_axe":54,"minecraft:stone_pickaxe":395,"minecraft:wooden_pickaxe":59,"minecraft:torch":8,"minecraft:cobblestone":10,"minecraft:crafting_table":3},"minecraft:mined":{"minecraft:large_fern":1,"minecraft:spruce_log":89,"minecraft:crafting_table":2,"minecraft:torch":3,"minecraft:coal_ore":22,"minecraft:copper_ore":3,"minecraft:cobblestone":2,"minecraft:spruce_leaves":9,"minecraft:stone":425,"minecraft:wall_torch":2},"minecraft:killed":{"minecraft:zombie":1}},"DataVersion":3465}